cursofiap/__init__.py
cursofiap/core.py
fiap_package-1.0.0.dist-info/METADATA
fiap_package-1.0.0.dist-info/WHEEL
fiap_package-1.0.0.dist-info/top_level.txt
fiap_package-1.0.0.dist-info/RECORD
